LICENSE
MANIFEST
MANIFEST.in
README.rst
builddocs.sh
setup.py
cookiesession/__init__.py
cookiesession/middleware.py
cookiesession/models.py
cookiesession/settings.py
cookiesession/tests.py
cookiesession/management/__init__.py
cookiesession/management/commands/__init__.py
cookiesession/management/commands/decode_session_cookie.py
cookiesession/management/commands/encode_session_cookie.py
django_cookiesession.egg-info/PKG-INFO
django_cookiesession.egg-info/SOURCES.txt
django_cookiesession.egg-info/dependency_links.txt
django_cookiesession.egg-info/top_level.txt
docs/Makefile
docs/conf.py
docs/getting_started.rst
docs/index.rst
docs/make.bat
docs/management_commands.rst
docs/settings.rst
docs/_build/doctrees/environment.pickle
docs/_build/doctrees/getting_started.doctree
docs/_build/doctrees/index.doctree
docs/_build/doctrees/management_commands.doctree
docs/_build/doctrees/settings.doctree
docs/_build/html/.buildinfo
docs/_build/html/genindex.html
docs/_build/html/getting_started.html
docs/_build/html/index.html
docs/_build/html/management_commands.html
docs/_build/html/objects.inv
docs/_build/html/search.html
docs/_build/html/searchindex.js
docs/_build/html/settings.html
docs/_build/html/_sources/getting_started.txt
docs/_build/html/_sources/index.txt
docs/_build/html/_sources/management_commands.txt
docs/_build/html/_sources/settings.txt
docs/_build/html/_static/basic.css
docs/_build/html/_static/breadcrumb_background.png
docs/_build/html/_static/default.css
docs/_build/html/_static/doctools.js
docs/_build/html/_static/documentation.png
docs/_build/html/_static/file.png
docs/_build/html/_static/header_sm_mid.png
docs/_build/html/_static/jquery.js
docs/_build/html/_static/minus.png
docs/_build/html/_static/plus.png
docs/_build/html/_static/pygments.css
docs/_build/html/_static/scrn1.png
docs/_build/html/_static/scrn2.png
docs/_build/html/_static/searchfield_leftcap.png
docs/_build/html/_static/searchfield_repeat.png
docs/_build/html/_static/searchfield_rightcap.png
docs/_build/html/_static/searchtools.js
docs/_build/html/_static/sidebar.js
docs/_build/html/_static/title_background.png
docs/_build/html/_static/toc.js
