Metadata-Version: 1.0
Name: django-cookiesession
Version: 0.1.1
Summary: A secure way to hold Django session data in cookies
Home-page: http://github.com/washingtontimes/django-cookiesession
Author: Justin Quick, The Washington Times
Author-email: jquick@washingtontimes.com
License: UNKNOWN
Platform: UNKNOWN
Classifier: Development Status :: 4 - Beta
Classifier: Framework :: Django
Classifier: Intended Audience :: Developers
Classifier: License :: OSI Approved :: Apache Software License
